[
	{
		"table": "#__easyblog_category",
		"column" : "repost_autoposting",
		"query" : "ALTER TABLE `#__easyblog_category` ADD COlUMN `repost_autoposting` tinyint(1) unsigned NOT NULL DEFAULT 0;"
	},
	{
		"table": "#__easyblog_category",
		"column" : "repost_autoposting_interval",
		"query" : "ALTER TABLE `#__easyblog_category` ADD COlUMN `repost_autoposting_interval` tinyint(4) unsigned NOT NULL DEFAULT 0;"
	},
	{
		"table": "#__easyblog_category",
		"index" : "idx_re_autopost",
		"query" : "ALTER TABLE `#__easyblog_category` ADD INDEX `idx_re_autopost` (`repost_autoposting`, `repost_autoposting_interval`);"
	}
]
